{
  "version": "2.0",
  "updated": "2026-06-29",
  "tasks": [
    {
      "id": "TASK-001",
      "title": "Multi-Tenant SaaS 框架完善与扩展",
      "status": "SUPERSEDED",
      "sprint": "sprint-001",
      "estimated_hours": 40,
      "created": "2026-06-27",
      "updated": "2026-06-28",
      "note": "AI循环超3轮FAIL，代码已提交(535cf30)，遗留问题移交后续Task"
    },
    {
      "id": "TASK-001a",
      "status": "SUPERSEDED",
      "updated": "2026-06-28"
    },
    {
      "id": "TASK-001b",
      "status": "SUPERSEDED",
      "updated": "2026-06-28"
    },
    {
      "id": "TASK-001c",
      "status": "SUPERSEDED",
      "updated": "2026-06-28"
    },
    {
      "id": "TASK-002",
      "title": "v0.2.2基座审查修复（6轮P0/P1/P2）",
      "status": "DONE",
      "sprint": "sprint-001",
      "created": "2026-06-24",
      "updated": "2026-06-28",
      "note": "v0.2.2→v0.2.3+2：RBAC权限/Factory/Mailable/TestCase索引/afterCommit/i18n/backoff/类型修复"
    },
    {
      "id": "TASK-003",
      "title": "TASK-001新增代码审查修复+安全加固",
      "status": "DONE",
      "sprint": "sprint-001",
      "estimated_hours": 4,
      "created": "2026-06-28",
      "updated": "2026-06-28",
      "depends_on": "TASK-001",
      "note": "ExportService fail-closed修复+AlertService租户过滤+审查误报5项关闭+SocialiteService决策+TASK-003任务文件生成"
    },
    {
      "id": "TASK-004",
      "title": "全量回归修复 + 支付宝OAuth认证模块接入",
      "status": "DONE",
      "sprint": "sprint-001",
      "estimated_hours": 8,
      "created": "2026-06-28",
      "updated": "2026-06-28T08:03:10.287952",
      "depends_on": "TASK-003",
      "auto_split": true,
      "human_confirmation": false,
      "note": "全量回归305tests全绿+AlipayOAuthService独立实现+22singleton注册+SocialiteService安全加固"
    },
    {
      "id": "TASK-004a",
      "status": "DONE",
      "updated": "2026-06-28T08:03:10.287952"
    },
    {
      "id": "TASK-004b",
      "status": "DONE",
      "updated": "2026-06-28T08:03:10.287952"
    },
    {
      "id": "TASK-004c",
      "status": "DONE",
      "updated": "2026-06-28T08:03:10.287952"
    },
    {
      "id": "TASK-009c",
      "status": "READY",
      "updated": "2026-06-28T20:14:46.706322"
    },
    {
      "id": "TASK-010",
      "status": "READY",
      "updated": "2026-06-28T22:59:19.220668"
    },
    {
      "id": "TASK-011",
      "status": "TEST",
      "updated": "2026-06-29T05:52:30.636042"
    },
    {
      "id": "TASK-011d",
      "status": "READY",
      "updated": "2026-06-28T22:40:30.572162"
    },
    {
      "id": "TASK-011a",
      "status": "READY",
      "updated": "2026-06-28T22:40:30.572162"
    },
    {
      "id": "TASK-011b",
      "status": "READY",
      "updated": "2026-06-28T22:40:30.572162"
    },
    {
      "id": "TASK-012",
      "status": "TEST",
      "updated": "2026-06-29T06:00:18.538295"
    },
    {
      "id": "TASK-013",
      "status": "TEST",
      "updated": "2026-06-29T06:05:22.106751"
    },
    {
      "id": "TASK-014",
      "status": "TEST",
      "updated": "2026-06-29T06:11:06.865381"
    },
    {
      "id": "TASK-015",
      "status": "TEST",
      "updated": "2026-06-29T06:28:52.483612"
    },
    {
      "id": "TASK-016",
      "status": "FAILED",
      "updated": "2026-06-29T06:52:50.828844"
    },
    {
      "id": "TASK-017",
      "status": "TEST",
      "updated": "2026-06-29T07:03:51.983623"
    },
    {
      "id": "TASK-018",
      "status": "TEST",
      "updated": "2026-06-29T07:31:55.619355"
    },
    {
      "id": "TASK-010a",
      "status": "DONE",
      "updated": "2026-06-28T23:39:06.494586"
    },
    {
      "id": "TASK-010c",
      "status": "TEST",
      "updated": "2026-06-29T05:40:31.130299"
    },
    {
      "id": "TASK-010d",
      "status": "TEST",
      "updated": "2026-06-29T05:47:05.530277"
    },
    {
      "id": "TASK-010b",
      "status": "TEST",
      "updated": "2026-06-29T05:32:03.061847"
    },
    {
      "id": "TASK-019",
      "status": "TEST",
      "updated": "2026-06-29T08:50:23.238459"
    },
    {
      "id": "TASK-020",
      "status": "TEST",
      "updated": "2026-06-29T10:10:13.579922"
    },
    {
      "id": "TASK-021",
      "status": "FAILED",
      "updated": "2026-06-29T10:51:18.210312"
    },
    {
      "id": "TASK-022",
      "status": "TEST",
      "updated": "2026-06-29T11:17:42.786865"
    },
    {
      "id": "TASK-023",
      "status": "TEST",
      "updated": "2026-06-29T11:51:33.257544"
    },
    {
      "id": "TASK-024",
      "status": "TEST",
      "updated": "2026-06-29T12:29:53.906590"
    },
    {
      "id": "TASK-025",
      "status": "TEST",
      "updated": "2026-06-29T12:51:44.143725"
    }
  ]
}
